fourwritersapi/__init__.py
fourwritersapi/const.py
fourwritersapi/api/__init__.py
fourwritersapi/api/api.py
fourwritersapi/client/__init__.py
fourwritersapi/client/aiohttp.py
fourwritersapi/client/storage.py
fourwritersapi/tools/__init__.py
fourwritersapi/types/__init__.py
fourwritersapi/types/models.py
fourwritersapi/utils/__init__.py
fourwritersapi-0.3.0.dist-info/METADATA
fourwritersapi-0.3.0.dist-info/WHEEL
fourwritersapi-0.3.0.dist-info/top_level.txt
fourwritersapi-0.3.0.dist-info/RECORD
