Metadata-Version: 2.1
Name: fourwritersapi
Version: 0.3.0
Summary: First library for parsing 4writers.net
Home-page: https://github.com/socalmy/4writersAPI
Author: socalmy
Author-email: sergeitoropov2003@gmail.com
License: MIT
Classifier: Programming Language :: Python :: 3
Classifier: License :: OSI Approved :: MIT License
Classifier: Operating System :: OS Independent
Requires-Python: >=3.6
Requires-Dist: envparse>=0.2.0
Requires-Dist: certifi>=2024.8.30
Requires-Dist: aiohttp>=3.11.10
Requires-Dist: lxml>=5.3.0
Requires-Dist: beautifulsoup4>=4.12.0
Requires-Dist: setuptools>=75.7.0
